src/__init__.py
src/cli.py
src/common.py
src/github_utils.py
src/scanner.py
src/utils.py
shai_hulud_detector-1.0.4.dist-info/METADATA
shai_hulud_detector-1.0.4.dist-info/WHEEL
shai_hulud_detector-1.0.4.dist-info/entry_points.txt
shai_hulud_detector-1.0.4.dist-info/licenses/LICENSE
shai_hulud_detector-1.0.4.dist-info/RECORD
