Metadata-Version: 2.4
Name: shai-hulud-detector
Version: 1.0.4
Summary: A CLI tool to detect potential Shai Hulud npm-worm compromises in GitHub users and organizations.
Project-URL: Homepage, https://github.com/ysskrishna/shai-hulud-detector
Project-URL: Documentation, https://github.com/ysskrishna/shai-hulud-detector#readme
Project-URL: Repository, https://github.com/ysskrishna/shai-hulud-detector.git
Project-URL: Issues, https://github.com/ysskrishna/shai-hulud-detector/issues
Author-email: ysskrishna <sivasaikrishnassk@gmail.com>
License: MIT
License-File: LICENSE
Keywords: cli,compromise,detection,devsecops,github,github-security,indicators-of-compromise,ioc,malware-detection,npm,npm-security,npm-worm,python-cli,repository-scanning,scanner,security,security-tool,shai-hulud,supply-chain-attack,supply-chain-security,threat-detection,vulnerability-scanner
Classifier: Development Status :: 5 - Production/Stable
Classifier: Intended Audience :: Developers
Classifier: Intended Audience :: System Administrators
Classifier: License :: OSI Approved :: MIT License
Classifier: Operating System :: OS Independent
Classifier: Programming Language :: Python :: 3
Classifier: Programming Language :: Python :: 3.11
Classifier: Programming Language :: Python :: 3.12
Classifier: Topic :: Security
Classifier: Topic :: Software Development :: Libraries :: Python Modules
Classifier: Topic :: Utilities
Requires-Python: >=3.11
Requires-Dist: pygithub>=2.1.0
Requires-Dist: typer>=0.9.0
